{"resumen":{"completados":2,"exitosos":1,"fallidos":1},"escenarios":[{"nombre":"Deja de recibir comando en pin 1 para pasar comando al pin 12","exitoso":false,"pasos":[{"nombre":"Preparacion","exitoso":true,"tiempo":6,"detalleDeError":""},{"nombre":"Recibe comando en el pin 1","exitoso":false,"tiempo":2,"detalleDeError":"Se esperaba que 32 sea igual a 40 pero no lo es"}]},{"nombre":"Deja de recibir comando en pin 1 para pasar comando al pin 12","exitoso":true,"pasos":[{"nombre":"Recibe comando en el pin 1","exitoso":true,"tiempo":100,"detalleDeError":""}]}]}
